dotpytree/__init__.py
dotpytree/cli.py
dotpytree/core.py
dotpytree-0.1.0.dist-info/licenses/LICENSE
dotpytree-0.1.0.dist-info/METADATA
dotpytree-0.1.0.dist-info/WHEEL
dotpytree-0.1.0.dist-info/entry_points.txt
dotpytree-0.1.0.dist-info/top_level.txt
dotpytree-0.1.0.dist-info/RECORD
