Metadata-Version: 2.4
Name: dotpytree
Version: 0.1.0
Summary: Print tree-style Python class/function outlines.
Author: Raybin
License: MIT
Project-URL: Homepage, https://github.com/rabin-HE/dotpytree
Requires-Python: >=3.7
License-File: LICENSE
Dynamic: license-file
